nyangsum/__init__.py
nyangsum/__main__.py
nyangsum/nyang.py
nyangsum-0.1.0.dist-info/METADATA
nyangsum-0.1.0.dist-info/WHEEL
nyangsum-0.1.0.dist-info/entry_points.txt
nyangsum-0.1.0.dist-info/licenses/LICENSE
nyangsum-0.1.0.dist-info/RECORD
