Metadata-Version: 2.4
Name: nyangsum
Version: 0.1.0
Summary: Korean cat-sound lorem ipsum generator: 냥, 냐옹, 냐앙, 냐아앙.
Project-URL: Homepage, https://github.com/jadhvank/nyang_lorem_ipsum
Project-URL: Repository, https://github.com/jadhvank/nyang_lorem_ipsum
Author: Nyangsum Authors
License: MIT
License-File: LICENSE
Keywords: cats,generator,ipsum,korean,lorem,nya,nyang,placeholder,text
Classifier: Development Status :: 3 - Alpha
Classifier: Environment :: Console
Classifier: Intended Audience :: Developers
Classifier: License :: OSI Approved :: MIT License
Classifier: Programming Language :: Python
Classifier: Programming Language :: Python :: 3
Classifier: Programming Language :: Python :: 3 :: Only
Classifier: Programming Language :: Python :: 3.8
Classifier: Programming Language :: Python :: 3.9
Classifier: Programming Language :: Python :: 3.10
Classifier: Programming Language :: Python :: 3.11
Classifier: Programming Language :: Python :: 3.12
Classifier: Topic :: Text Processing
Classifier: Topic :: Utilities
Requires-Python: >=3.8
